encoder8x3.v
// // module encoder8x3(input [7:0]a, output [2:0]y);
// // assign y[0]= a[4] | a[5] | a[6] | a[7];
// // assign y[1]= a[2] | a[3] | a[6] | a[7];  this code is wrong when we assign wrong way
// // assign y[2]= a[1] | a[3] | a[5] | a[7];
// // endmodule
 
// //DATA- FLOW:
// module encoder8x3(input [7:0]a, output [2:0]y);
// assign y[2] = a[7] | a[6] | a[5] | a[4];
// assign y[1] = a[7] | a[6] | a[3] | a[2];
// assign y[0] = a[7] | a[5] | a[3] | a[1];
// endmodule

// //BEHAVIOURAL -MODEL:

// module encoder8x3(input [7:0] a, output reg [2:0] y);
//   always @(a) begin
//     if (a[0]) y = 3'b000;
//     else if (a[1]) y = 3'b001;
//     else if (a[2]) y = 3'b010;
//     else if (a[3]) y = 3'b011;
//     else if (a[4]) y = 3'b100;
//     else if (a[5]) y = 3'b101;
//     else if (a[6]) y = 3'b110;
//     else if (a[7]) y = 3'b111;
//     else y = 3'b000; // Default case, handles when no input is active. 
//   end
// endmodule

//GATE -LEVEL:
module encoder8x3(input [7:0] a, output [2:0] y);
wire w1, w2, w3;
  or (w1, a[7], a[6], a[5], a[4]);
  or (w2, a[7], a[6], a[3], a[2]);
  or (w3, a[7], a[5], a[3], a[1]);
assign y[2]=w1;
assign y[1]=w2;
assign y[0]=w3;
endmodule

encoder8x3_tb.v
`include "encoder8x3.v"
module encoder8x3_tb;
reg [7:0] a;
wire [2:0] y;
encoder8x3 dut(a, y);
initial begin
$dumpfile("encoder8x3_tb.vcd");
$dumpvars(1, encoder8x3_tb);
$monitor("Time=%0t | a=%b -> y=%b", $time, a, y);

a = 8'b0000_0001; #10; //000
a = 8'b0000_0010; #10;  // 001
a = 8'b0000_0100; #10;  // 010
a = 8'b0000_1000; #10;  //011
a = 8'b0001_0000; #10;  //100
a = 8'b0010_0000; #10;   //101
a = 8'b0100_0000; #10;  //110
a = 8'b1000_0000; #10;  //111

$finish;
  end
  endmodule

encoder8x3_tb.vcd
$date
	Mon Apr 28 06:32:55 2025
$end
$version
	Icarus Verilog
$end
$timescale
	1s
$end
$scope module encoder8x3_tb $end
$var wire 3 ! y [2:0] $end
$var reg 8 " a [7:0] $end
$upscope $end
$enddefinitions $end
#0
$dumpvars
b1 "
b0 !
$end
#10
b1 !
b10 "
#20
b10 !
b100 "
#30
b11 !
b1000 "
#40
b100 !
b10000 "
#50
b101 !
b100000 "
#60
b110 !
b1000000 "
#70
b111 !
b10000000 "
