pe8x3.v
// // DATA FLOW MODELING

// module pe8x3(input [7:0]a, output [2:0]y);
// assign y[2]=a[7] | a[6] | a[5] |a[4];
// assign y[1]= ~a[5]& ~a[4] & (a[2] | a[3]) | a[6] | a[7];
// assign y[0]= ~a[6] & ((~a[4] & ~a[2]& a[1] | ~a[4] & a[3]) |a[5]) | a[7];
// endmodule

// // BEHAVIOURAL MODELING
// module pe8x3(input [7:0] a, output reg [2:0] y);
//   always @(a) begin
//     case (1'b1)  // Use '1' as the condition to always evaluate the cases
//       a[7]: y = 3'b111;
//       a[6]: y = 3'b110;
//       a[5]: y = 3'b101;
//       a[4]: y = 3'b100;
//       a[3]: y = 3'b011;
//       a[2]: y = 3'b010;
//       a[1]: y = 3'b001;
//       default: y = 3'b000; //Handles the case where no input is high
//     endcase
//   end
// endmodule


// GATE -LEVEL MODELING: 
module pe8x3(input [7:0] a, output [2:0] y);
  wire w1, w2, w3, w4, w5, w6, w7, w8, w9, w10, w11, w12, w13;

  // Calculate y[2]
  or (w1, a[4], a[5]);
  or (w2, w1, a[6]);
  or (y[2], w2, a[7]);

  // Calculate y[1]
  not (w3, a[5]);
  not (w4, a[4]);
  and (w5, w3, w4);
  or  (w6, a[2], a[3]);
  and (w7, w5, w6);
  or  (y[1], a[6], a[7], w7);

  // Calculate y[0]
  not (w8, a[6]);
  not (w9, a[4]);
  not (w10, a[2]);
  and (w11, w9, w10);
  and (w12, w11, a[1]);
  and (w13, w9, a[3]);
  or  (w14, w12, w13);
  and (w15, w8, w14);
  or  (y[0], a[5], a[7], w15);

endmodule

pe8x3_tb.v
`include "pe8x3.v"
module pe8x3_tb;
reg [7:0] a;
wire [2:0] y;
pe8x3 dut(a, y);
initial begin
$dumpfile("pe8x3_tb.vcd");
$dumpvars(1, pe8x3_tb);
$monitor("Time=%0t | a=%b -> y=%b", $time, a, y);

a = 8'b0000_0001; #10; //000
a = 8'b0000_0010; #10;  // 001
a = 8'b0000_0100; #10;  // 010
a = 8'b0000_1000; #10;  //011
a = 8'b0001_0000; #10;  //100
a = 8'b0010_0000; #10;   //101
a = 8'b0100_0000; #10;  //110
a = 8'b1000_0000; #10;  //111


 // Test cases with multiple inputs asserted (higher priority should win)
    a = 8'b00000011; #10; // a[1] should be prioritized over a[0] -> y = 001
    a = 8'b00000101; #10; // a[2] should be prioritized over a[0] -> y = 010
    a = 8'b00001100; #10; // a[3] should be prioritized over a[2] -> y = 011
    a = 8'b00110000; #10; // a[5] should be prioritized over a[4] -> y = 101
    a = 8'b11000000; #10; // a[7] should be prioritized over a[6] -> y = 111
    a = 8'b10101010; #10; // a[7] should have the highest priority -> y = 111
 $finish;

 end
 endmodule

pe8x3_tb.vcd
$date
	Sun Apr 27 20:50:52 2025
$end
$version
	Icarus Verilog
$end
$timescale
	1s
$end
$scope module pe8x3_tb $end
$var wire 3 ! y [2:0] $end
$var reg 8 " a [7:0] $end
$upscope $end
$enddefinitions $end
#0
$dumpvars
b1 "
b0 !
$end
#10
b1 !
b10 "
#20
b10 !
b100 "
#30
b11 !
b1000 "
#40
b100 !
b10000 "
#50
b101 !
b100000 "
#60
b110 !
b1000000 "
#70
b111 !
b10000000 "
#80
b1 !
b11 "
#90
b10 !
b101 "
#100
b11 !
b1100 "
#110
b101 !
b110000 "
#120
b111 !
b11000000 "
#130
b10101010 "
